reticuler/__init__.py
reticuler/system.py
reticuler/backward_evolution/__init__.py
reticuler/backward_evolution/system_back.py
reticuler/backward_evolution/trimmers.py
reticuler/extending_kernels/__init__.py
reticuler/extending_kernels/extenders.py
reticuler/extending_kernels/pde_solvers/__init__.py
reticuler/extending_kernels/pde_solvers/freefem.py
reticuler/extending_kernels/pde_solvers/freefem_thickfingers.py
reticuler/extending_kernels/pde_solvers/freefem_thinfingers.py
reticuler/user_interface/__init__.py
reticuler/user_interface/clip_ret.py
reticuler/user_interface/clippers.py
reticuler/user_interface/graphics.py
reticuler/user_interface/plot_ret.py
reticuler/user_interface/reticulate.py
reticuler/user_interface/reticulate_back.py
reticuler/user_interface/script_ret.py
reticuler/utilities/__init__.py
reticuler/utilities/misc.py
reticuler/utilities/morphers.py
reticuler/utilities/geometry/__init__.py
reticuler/utilities/geometry/box.py
reticuler/utilities/geometry/branch.py
reticuler/utilities/geometry/network.py
reticuler-5.0.dist-info/LICENSE
reticuler-5.0.dist-info/METADATA
reticuler-5.0.dist-info/WHEEL
reticuler-5.0.dist-info/entry_points.txt
reticuler-5.0.dist-info/top_level.txt
reticuler-5.0.dist-info/RECORD
