Metadata-Version: 2.1
Name: reticuler
Version: 5.0
Summary: Simulations of spatial networks growth
Author: Stanisław Żukowski
Author-email: zukowski.st@gmail.com
License: MIT
Project-URL: Source, https://github.com/stzukowski/reticuler
Classifier: Programming Language :: Python :: 3
Classifier: License :: OSI Approved :: MIT License
Classifier: Operating System :: OS Independent
Requires-Python: >=3.9
License-File: LICENSE
Requires-Dist: numpy>=1.23
Requires-Dist: matplotlib>=3.6
Requires-Dist: scipy>=1.11.4
Requires-Dist: shapely>=2.0.3
